waba_360/__init__.py
waba_360/client.py
waba_360/server.py
waba_360-0.0.2.dist-info/METADATA
waba_360-0.0.2.dist-info/WHEEL
waba_360-0.0.2.dist-info/top_level.txt
waba_360-0.0.2.dist-info/RECORD
