Metadata-Version: 2.1
Name: waba-360
Version: 0.0.2
Summary: Async HTTP Client for Waba360 interacting
Author: Mike Artemiev
Author-email: <mixartemev@gmail.com>
Keywords: whatsapp,http-client,api
Classifier: Development Status :: 1 - Planning
Classifier: Intended Audience :: Developers
Classifier: Programming Language :: Python :: 3
Classifier: Operating System :: Unix
Classifier: Operating System :: MacOS :: MacOS X
Requires-Dist: aiohttp
Requires-Dist: python-dotenv
